eeveon/__init__.py
eeveon/api.py
eeveon/cli.py
eeveon/dashboard/index.html
eeveon/dashboard/static/style.css
eeveon/scripts/deploy.sh
eeveon/scripts/health_check.sh
eeveon/scripts/monitor.sh
eeveon/scripts/notify.sh
eeveon/scripts/rollback.sh
eeveon-0.4.0.data/data/scripts/deploy.sh
eeveon-0.4.0.data/data/scripts/health_check.sh
eeveon-0.4.0.data/data/scripts/monitor.sh
eeveon-0.4.0.data/data/scripts/notify.sh
eeveon-0.4.0.data/data/scripts/rollback.sh
eeveon-0.4.0.dist-info/LICENSE
eeveon-0.4.0.dist-info/METADATA
eeveon-0.4.0.dist-info/WHEEL
eeveon-0.4.0.dist-info/entry_points.txt
eeveon-0.4.0.dist-info/top_level.txt
eeveon-0.4.0.dist-info/RECORD
