Metadata-Version: 2.1
Name: eeveon
Version: 0.4.0
Summary: Lightweight bash-based CI/CD pipeline for automatic deployment from GitHub
Home-page: https://github.com/adarsh-crypto/eeveon
Author: Adarsh
Author-email: Adarsh <sinha.adarsh200@gmail.com>
Maintainer-email: Adarsh <sinha.adarsh200@gmail.com>
License: MIT
Project-URL: Homepage, https://github.com/adarsh-crypto/eeveon
Project-URL: Documentation, https://github.com/adarsh-crypto/eeveon#readme
Project-URL: Repository, https://github.com/adarsh-crypto/eeveon
Project-URL: Bug Tracker, https://github.com/adarsh-crypto/eeveon/issues
Project-URL: Changelog, https://github.com/adarsh-crypto/eeveon/blob/main/CHANGELOG.md
Keywords: ci,cd,deployment,automation,github,devops,pipeline,continuous-deployment,continuous-integration
Classifier: Development Status :: 4 - Beta
Classifier: Intended Audience :: Developers
Classifier: Intended Audience :: System Administrators
Classifier: Topic :: Software Development :: Build Tools
Classifier: Topic :: System :: Systems Administration
Classifier: Programming Language :: Python :: 3
Classifier: Programming Language :: Python :: 3.6
Classifier: Programming Language :: Python :: 3.7
Classifier: Programming Language :: Python :: 3.8
Classifier: Programming Language :: Python :: 3.9
Classifier: Programming Language :: Python :: 3.10
Classifier: Programming Language :: Python :: 3.11
Classifier: Programming Language :: Python :: 3.12
Classifier: Programming Language :: Unix Shell
Classifier: Operating System :: POSIX :: Linux
Classifier: Operating System :: Unix
Requires-Python: >=3.6
License-File: LICENSE
Requires-Dist: cryptography>=3.0.0
Requires-Dist: fastapi>=0.100.0
Requires-Dist: uvicorn>=0.20.0
Provides-Extra: dev
Requires-Dist: black>=22.0.0; extra == "dev"
Requires-Dist: isort>=5.0.0; extra == "dev"
Requires-Dist: flake8>=4.0.0; extra == "dev"
Requires-Dist: mypy>=0.950; extra == "dev"
Provides-Extra: docs
Requires-Dist: sphinx>=4.0.0; extra == "docs"
Requires-Dist: sphinx-rtd-theme>=1.0.0; extra == "docs"
Provides-Extra: monitoring
Requires-Dist: psutil>=5.0.0; extra == "monitoring"
Provides-Extra: premium
Requires-Dist: rich>=13.0.0; extra == "premium"
Requires-Dist: psutil>=5.0.0; extra == "premium"
Provides-Extra: rich
Requires-Dist: rich>=13.0.0; extra == "rich"
